poodle/__init__.py
poodle/cli.py
poodle/config.py
poodle/core.py
poodle/mutate.py
poodle/report.py
poodle/run.py
poodle/util.py
poodle/data_types/__init__.py
poodle/data_types/data.py
poodle/data_types/interfaces.py
poodle/data_types/work.py
poodle/mutators/__init__.py
poodle/mutators/calls.py
poodle/mutators/compare.py
poodle/mutators/constant.py
poodle/mutators/operators.py
poodle/mutators/unary_op.py
poodle/reporters/__init__.py
poodle/reporters/basic.py
poodle/runners/__init__.py
poodle/runners/command_line.py
poodle_test-0.0.1a6.dist-info/LICENSE
poodle_test-0.0.1a6.dist-info/METADATA
poodle_test-0.0.1a6.dist-info/WHEEL
poodle_test-0.0.1a6.dist-info/entry_points.txt
poodle_test-0.0.1a6.dist-info/top_level.txt
poodle_test-0.0.1a6.dist-info/RECORD
