Metadata-Version: 2.1
Name: poodle-test
Version: 0.0.1a6
Summary: Mutation Testing Tool
Author-email: WiredNerd <pbuschmail-poodle@yahoo.com>
Maintainer-email: WiredNerd <pbuschmail-poodle@yahoo.com>
License: MIT License
Project-URL: Documentation, https://poodle.readthedocs.io/
Project-URL: Homepage, https://github.com/WiredNerd/poodle
Project-URL: Issue Tracker, https://github.com/WiredNerd/poodle/issues
Keywords: test,coverage,quality,mutation,pytest,pit,pitest,pittest,mutmut,mutatest
Classifier: Programming Language :: Python :: 3
Classifier: License :: OSI Approved :: MIT License
Classifier: Operating System :: OS Independent
Requires-Python: >=3.9
License-File: LICENSE
Requires-Dist: click >=8
Requires-Dist: tomli >=2 ; python_version < "3.11"
